odoo/addons/mrp_production_service/README.rst
odoo/addons/mrp_production_service/__init__.py
odoo/addons/mrp_production_service/__manifest__.py
odoo/addons/mrp_production_service/models/__init__.py
odoo/addons/mrp_production_service/models/mrp_production.py
odoo/addons/mrp_production_service/static/description/icon.png
odoo/addons/mrp_production_service/tests/__init__.py
odoo/addons/mrp_production_service/tests/test_mrp_production_service.py
odoo11_addon_mrp_production_service-11.0.1.0.1.dist-info/DESCRIPTION.rst
odoo11_addon_mrp_production_service-11.0.1.0.1.dist-info/METADATA
odoo11_addon_mrp_production_service-11.0.1.0.1.dist-info/RECORD
odoo11_addon_mrp_production_service-11.0.1.0.1.dist-info/WHEEL
odoo11_addon_mrp_production_service-11.0.1.0.1.dist-info/metadata.json
odoo11_addon_mrp_production_service-11.0.1.0.1.dist-info/top_level.txt
