Metadata-Version: 2.0
Name: odoo11-addon-mrp-production-service
Version: 11.0.1.0.1
Summary: Creates procurement orders from manufacturing orders, for services included in the Bill of Materials
Home-page: https://www.odoo-community.org
Author: Eficent,Odoo Community Association (OCA)
Author-email: support@odoo-community.org
License: AGPL-3
Platform: UNKNOWN
Classifier: Programming Language :: Python
Classifier: Framework :: Odoo
Classifier: License :: OSI Approved :: GNU Affero General Public License v3
Requires-Python: >=2.7, !=3.0.*, !=3.1.*, !=3.2.*, !=3.3.*, !=3.4.*
Requires-Dist: odoo (<11.1dev,>=11.0a)
Requires-Dist: odoo11-addon-subcontracted-service
